FLAI/__init__.py
FLAI/causal_graph.py
FLAI/data.py
FLAI_CAUSAL-3.0.4.dist-info/LICENSE
FLAI_CAUSAL-3.0.4.dist-info/METADATA
FLAI_CAUSAL-3.0.4.dist-info/WHEEL
FLAI_CAUSAL-3.0.4.dist-info/top_level.txt
FLAI_CAUSAL-3.0.4.dist-info/RECORD
