Metadata-Version: 2.1
Name: FLAI_CAUSAL
Version: 3.0.4
Summary: Library to creat causal model and mitigate the bias.
Home-page: https://github.com/rugonzs/FLAI
Author: Rubén González Sendino
Author-email: rubo.g@icloud.com
License: Apache-2.0 license
Project-URL: Documentation, https://rugonzs.github.io/FLAI/
Project-URL: Source Code, https://github.com/rugonzs/FLAI
License-File: LICENSE
Requires-Dist: scikit-learn==1.5.2
Requires-Dist: bnlearn==0.10.2
Requires-Dist: networkx==3.4.2
Requires-Dist: matplotlib==3.9.2
Requires-Dist: pgmpy==0.1.26
Requires-Dist: numpy==1.26.4
Requires-Dist: pandas==2.2.3
Requires-Dist: scipy==1.11.4
Requires-Dist: statsmodels==0.14.4
